AUTHORS.rst
CONTRIBUTING.rst
HISTORY.rst
LICENSE
MANIFEST.in
README.rst
setup.py
django_filtered_feed.egg-info/PKG-INFO
django_filtered_feed.egg-info/SOURCES.txt
django_filtered_feed.egg-info/dependency_links.txt
django_filtered_feed.egg-info/not-zip-safe
django_filtered_feed.egg-info/requires.txt
django_filtered_feed.egg-info/top_level.txt
filtered_feed/__init__.py
filtered_feed/models.py
filtered_feed/viewmixins.py
filtered_feed/views.py
filtered_feed/static/js/filtered_feed.js
filtered_feed/templates/filtered_feed/base.html
filtered_feed/testproject/manage.py
filtered_feed/testproject/testapp/__init__.py
filtered_feed/testproject/testapp/admin.py
filtered_feed/testproject/testapp/models.py
filtered_feed/testproject/testapp/tests.py
filtered_feed/testproject/testapp/urls.py
filtered_feed/testproject/testapp/views.py
filtered_feed/testproject/testapp/.ropeproject/config.py
filtered_feed/testproject/testapp/templates/base.html
filtered_feed/testproject/testapp/templates/testapp/book_detail.html
filtered_feed/testproject/testapp/templates/testapp/book_list.html
filtered_feed/testproject/testapp/templates/testapp/home.html
filtered_feed/testproject/testproject/__init__.py
filtered_feed/testproject/testproject/settings.py
filtered_feed/testproject/testproject/urls.py
filtered_feed/testproject/testproject/wsgi.py
filtered_feed/testproject/testproject/.ropeproject/config.py